SevenSeg/dff_1.v
module dff_1 (clk, Din, Load, Q4, rst);
input clk, Load ,rst;
input [3:0] Din;
output [3:0] Q4;
reg [3:0]Q4;

always@ (posedge clk)
  if(!rst)
    	Q4=0;
	else if (Load) begin
    	Q4 = Din;
	end
	else if(Q4==9)
		Q4 = 0;
	else Q4 = Q4+1;
endmodule

SevenSeg/sevenseg.v
module sevenseg(clk, rst, Din ,load ,out);
input [3:0] Din;
input clk,rst,load;
wire [3:0] Q;
output reg [7:0] out;

dff_1 dff(clk, Din, load, Q, rst);

always @(*)
begin
case (Q)
    4'b0000:out=8'b11000000;
    4'b0001:out=8'b11111001;
    4'b0010:out=8'b10100100;
    4'b0011:out=8'b10110000;
    4'b0100:out=8'b10011001;
    4'b0101:out=8'b10010010;
    4'b0110:out=8'b10000010;
    4'b0111:out=8'b11111000;
    4'b1000:out=8'b10000000;
    4'b1001:out=8'b00100000;
    default:out=8'b00000000;
endcase
end

endmodule

SevenSeg/sevenseg_tb.v
`timescale 1ns/1ps
module BCD_tb;
reg clk,load;
reg [3:0]din;
reg rst_n;
wire [7:0] out;

parameter PERIOD = 20;
parameter real DUTY_CYCLE = 0.5;
parameter OFFSET = 0;

initial begin
  #OFFSET;
    forever
    begin
    clk = 1'b1;
    #(PERIOD-(PERIOD*DUTY_CYCLE)) clk = 1'b0;
    #(PERIOD*DUTY_CYCLE);
  end
end

initial begin
	rst_n = 0;
	load  = 0;
	din = 4'b0110;
	#5 rst_n = 1'b1;
  #150 load = 1;
	#151 load = 0;
	#500 $finish;
end

initial begin
	$dumpfile("sevenseg.vcd");
	$dumpvars(0, dff_0);
end

sevenseg dff_0(.clk(clk),
        .rst(rst_n),
        .Din(din),
        .load(load),
        .out(out));

endmodule

SevenSeg/sevenseg.vcd
$date
	Wed May 04 23:10:12 2022
$end
$version
	Icarus Verilog
$end
$timescale
	1ps
$end
$scope module BCD_tb $end
$scope module dff_0 $end
$var wire 4 ! Din [3:0] $end
$var wire 1 " clk $end
$var wire 1 # load $end
$var wire 1 $ rst $end
$var wire 4 % Q [3:0] $end
$var reg 8 & out [7:0] $end
$scope module dff $end
$var wire 4 ' Din [3:0] $end
$var wire 1 # Load $end
$var wire 1 " clk $end
$var wire 1 $ rst $end
$var reg 4 ( Q4 [3:0] $end
$upscope $end
$upscope $end
$upscope $end
$enddefinitions $end
#0
$dumpvars
b0 (
b110 '
b11000000 &
b0 %
0$
0#
1"
b110 !
$end
#5000
1$
#10000
0"
#20000
b11111001 &
b1 %
b1 (
1"
#30000
0"
#40000
b10100100 &
b10 %
b10 (
1"
#50000
0"
#60000
b10110000 &
b11 %
b11 (
1"
#70000
0"
#80000
b10011001 &
b100 %
b100 (
1"
#90000
0"
#100000
b10010010 &
b101 %
b101 (
1"
#110000
0"
#120000
b10000010 &
b110 %
b110 (
1"
#130000
0"
#140000
b11111000 &
b111 %
b111 (
1"
#150000
0"
#155000
1#
#160000
b10000010 &
b110 %
b110 (
1"
#170000
0"
#180000
1"
#190000
0"
#200000
1"
#210000
0"
#220000
1"
#230000
0"
#240000
1"
#250000
0"
#260000
1"
#270000
0"
#280000
1"
#290000
0"
#300000
1"
#306000
0#
#310000
0"
#320000
b11111000 &
b111 %
b111 (
1"
#330000
0"
#340000
b10000000 &
b1000 %
b1000 (
1"
#350000
0"
#360000
b100000 &
b1001 %
b1001 (
1"
#370000
0"
#380000
b11000000 &
b0 %
b0 (
1"
#390000
0"
#400000
b11111001 &
b1 %
b1 (
1"
#410000
0"
#420000
b10100100 &
b10 %
b10 (
1"
#430000
0"
#440000
b10110000 &
b11 %
b11 (
1"
#450000
0"
#460000
b10011001 &
b100 %
b100 (
1"
#470000
0"
#480000
b10010010 &
b101 %
b101 (
1"
#490000
0"
#500000
b10000010 &
b110 %
b110 (
1"
#510000
0"
#520000
b11111000 &
b111 %
b111 (
1"
#530000
0"
#540000
b10000000 &
b1000 %
b1000 (
1"
#550000
0"
#560000
b100000 &
b1001 %
b1001 (
1"
#570000
0"
#580000
b11000000 &
b0 %
b0 (
1"
#590000
0"
#600000
b11111001 &
b1 %
b1 (
1"
#610000
0"
#620000
b10100100 &
b10 %
b10 (
1"
#630000
0"
#640000
b10110000 &
b11 %
b11 (
1"
#650000
0"
#660000
b10011001 &
b100 %
b100 (
1"
#670000
0"
#680000
b10010010 &
b101 %
b101 (
1"
#690000
0"
#700000
b10000010 &
b110 %
b110 (
1"
#710000
0"
#720000
b11111000 &
b111 %
b111 (
1"
#730000
0"
#740000
b10000000 &
b1000 %
b1000 (
1"
#750000
0"
#760000
b100000 &
b1001 %
b1001 (
1"
#770000
0"
#780000
b11000000 &
b0 %
b0 (
1"
#790000
0"
#800000
b11111001 &
b1 %
b1 (
1"
